cli/__init__.py
cli/cli.py
cowgirl_ai/__init__.py
cowgirl_ai/client.py
cowgirl_ai/error_handler.py
cowgirl_ai/assistants/__init__.py
cowgirl_ai/assistants/assistant_interactions.py
cowgirl_ai/search/__init__.py
cowgirl_ai/search/search.py
cowgirl_ai/vectors/__init__.py
cowgirl_ai/vectors/vector_interactions.py
cowgirl_ai-1.1.3.dist-info/LICENSE
cowgirl_ai-1.1.3.dist-info/METADATA
cowgirl_ai-1.1.3.dist-info/WHEEL
cowgirl_ai-1.1.3.dist-info/entry_points.txt
cowgirl_ai-1.1.3.dist-info/top_level.txt
cowgirl_ai-1.1.3.dist-info/RECORD
