Metadata-Version: 2.1
Name: cowgirl-ai
Version: 1.1.3
Summary: Interacting with the Open AI API
Home-page: https://github.com/Cowgirl-AI/file-management
Author: Tera Earlywine
Author-email: dev@teraearlywine.com
Requires-Python: >=3.10
License-File: LICENSE
